atprototools
tests
