Metadata-Version: 1.1
Name: atprototools
Version: 0.0.11
Summary: Easy-to-use and ergonomic library for interacting with bluesky, packaged so you can `pip install atprototools` and go.
Home-page: https://github.com/ianklatzco/atprototools
Author: Ian Klatzco
Author-email: iklatzco@gmail.com
License: UNKNOWN
Platform: UNKNOWN
Classifier: Development Status :: 3 - Alpha
Classifier: Intended Audience :: Developers
Classifier: License :: OSI Approved :: MIT License
Classifier: Programming Language :: Python :: 3
Classifier: Programming Language :: Python :: 3.7
Classifier: Programming Language :: Python :: 3.8
Classifier: Programming Language :: Python :: 3.9
